envmgr/__init__.py
envmgr/ami.py
envmgr/asg.py
envmgr/client.py
envmgr/instance.py
envmgr/service.py
envmgr/upstream.py
envmgr/utils.py
envmgr_lib-0.3.0.dist-info/DESCRIPTION.rst
envmgr_lib-0.3.0.dist-info/METADATA
envmgr_lib-0.3.0.dist-info/RECORD
envmgr_lib-0.3.0.dist-info/WHEEL
envmgr_lib-0.3.0.dist-info/metadata.json
envmgr_lib-0.3.0.dist-info/top_level.txt
envmgr_lib-0.3.0.dist-info/zip-safe
