Metadata-Version: 2.0
Name: envmgr-lib
Version: 0.3.0
Summary: Tools for the EM API
Home-page: https://github.com/trainline/envmgr-lib
Author: Trainline Engineering
Author-email: platform.development@thetrainline.com
License: Apache 2.0
Platform: UNKNOWN
Requires-Dist: environment-manager (==0.2.5)
Requires-Dist: python-dateutil
Requires-Dist: repoze.lru
Requires-Dist: requests
Requires-Dist: simplejson
